ai_infra_bench/__init__.py
ai_infra_bench/api.py
ai_infra_bench/check.py
ai_infra_bench/cli.py
ai_infra_bench/client.py
ai_infra_bench/utils.py
ai_infra_bench/version.py
ai_infra_bench/examples/client_gen.py
ai_infra_bench/examples/cmp_bench.py
ai_infra_bench/examples/gen_bench.py
ai_infra_bench/examples/slo_bench.py
ai_infra_bench/modes/cmp.py
ai_infra_bench/modes/common.py
ai_infra_bench/modes/gen.py
ai_infra_bench/modes/slo.py
ai_infra_bench/sgl/__init__.py
ai_infra_bench/sgl/cmp_bench.py
ai_infra_bench/sgl/gen_bench.py
ai_infra_bench/sgl/slo_bench.py
ai_infra_bench-0.1.3.post2.dist-info/licenses/LICENSE
ai_infra_bench-0.1.3.post2.dist-info/METADATA
ai_infra_bench-0.1.3.post2.dist-info/WHEEL
ai_infra_bench-0.1.3.post2.dist-info/entry_points.txt
ai_infra_bench-0.1.3.post2.dist-info/top_level.txt
ai_infra_bench-0.1.3.post2.dist-info/RECORD
