Metadata-Version: 2.4
Name: ai-infra-bench
Version: 0.1.3.post2
Summary: AI Infra bench
Requires-Python: >=3.10
License-File: LICENSE
Requires-Dist: plotly
Requires-Dist: numpy
Requires-Dist: psutil
Requires-Dist: requests
Requires-Dist: tqdm
Dynamic: license-file
